tinyurl_mcp/__init__.py
tinyurl_mcp/main.py
tinyurl_mcp/models.py
tinyurl_mcp/prompts.py
tinyurl_mcp/server.py
tinyurl_mcp/tools.py
tinyurl_mcp/utils.py
tinyurl_mcp-1.0.1.dist-info/METADATA
tinyurl_mcp-1.0.1.dist-info/WHEEL
tinyurl_mcp-1.0.1.dist-info/entry_points.txt
tinyurl_mcp-1.0.1.dist-info/RECORD
