Metadata-Version: 2.4
Name: tinyurl-mcp
Version: 1.0.1
Summary: MCP Server for tinyurl.com
Author-email: Vimal Paliwal <vimalpaliwal.me@gmail.com>
License-Expression: Apache-2.0
Keywords: mcp,tinyurl,url shortener
Requires-Python: >=3.13
Requires-Dist: dateparser>=1.2.2
Requires-Dist: httpx>=0.28.1
Requires-Dist: loguru>=0.7.3
Requires-Dist: mcp[cli]>=1.13.1
Requires-Dist: pydantic>=2.11.7
